{
    "1": {
        "year": "2008",
        "color": "#ffd300",
        "x": "1",
        "y": "6.4",
        "percCov": "10.6494057226396"
    },
    "2": {
        "year": "2008",
        "color": "#e41a1c",
        "x": "1",
        "y": "1.9",
        "percCov": "0.328198079000654"
    },
    "3": {
        "year": "2008",
        "color": "#f781bf",
        "x": "1",
        "y": "4.6",
        "percCov": "4.94034938924798"
    },
    "4": {
        "year": "2008",
        "color": "#AAAAAA",
        "x": "1",
        "y": "1",
        "percCov": "80.0960529791272"
    },
    "5": {
        "year": "2008",
        "color": "#4daf4a",
        "x": "1",
        "y": "5.5",
        "percCov": "3.49630193620904"
    },
    "6": {
        "year": "2008",
        "color": "#a65628",
        "x": "1",
        "y": "3.7",
        "percCov": "0.483818843816326"
    },
    "7": {
        "year": "2008",
        "color": "#377eb8",
        "x": "1",
        "y": "2.8",
        "percCov": "0.00587304995917477"
    },
    "8": {
        "year": "2009",
        "color": "#ffd300",
        "x": "2",
        "y": "6.4",
        "percCov": "10.9423655018852"
    },
    "9": {
        "year": "2009",
        "color": "#e41a1c",
        "x": "2",
        "y": "1.9",
        "percCov": "0.429425365732892"
    },
    "10": {
        "year": "2009",
        "color": "#f781bf",
        "x": "2",
        "y": "4.6",
        "percCov": "4.20799511844135"
    },
    "11": {
        "year": "2009",
        "color": "#AAAAAA",
        "x": "2",
        "y": "1",
        "percCov": "80.9777333099214"
    },
    "12": {
        "year": "2009",
        "color": "#4daf4a",
        "x": "2",
        "y": "5.5",
        "percCov": "2.95131301820254"
    },
    "13": {
        "year": "2009",
        "color": "#a65628",
        "x": "2",
        "y": "3.7",
        "percCov": "0.486981255332805"
    },
    "14": {
        "year": "2009",
        "color": "#377eb8",
        "x": "2",
        "y": "2.8",
        "percCov": "0.00418643048371945"
    },
    "15": {
        "year": "2010",
        "color": "#ffd300",
        "x": "3",
        "y": "6.4",
        "percCov": "10.3918950705835"
    },
    "16": {
        "year": "2010",
        "color": "#e41a1c",
        "x": "3",
        "y": "1.9",
        "percCov": "0.520442580997641"
    },
    "17": {
        "year": "2010",
        "color": "#f781bf",
        "x": "3",
        "y": "4.6",
        "percCov": "3.38158169367316"
    },
    "18": {
        "year": "2010",
        "color": "#AAAAAA",
        "x": "3",
        "y": "1",
        "percCov": "82.2036647229381"
    },
    "19": {
        "year": "2010",
        "color": "#4daf4a",
        "x": "3",
        "y": "5.5",
        "percCov": "3.26303643911259"
    },
    "20": {
        "year": "2010",
        "color": "#a65628",
        "x": "3",
        "y": "3.7",
        "percCov": "0.238626537572009"
    },
    "21": {
        "year": "2010",
        "color": "#377eb8",
        "x": "3",
        "y": "2.8",
        "percCov": "0.000752955122971125"
    },
    "22": {
        "year": "2011",
        "color": "#ffd300",
        "x": "4",
        "y": "6.4",
        "percCov": "14.3885507451093"
    },
    "23": {
        "year": "2011",
        "color": "#e41a1c",
        "x": "4",
        "y": "1.9",
        "percCov": "0.46755501316015"
    },
    "24": {
        "year": "2011",
        "color": "#f781bf",
        "x": "4",
        "y": "4.6",
        "percCov": "14.908993326107"
    },
    "25": {
        "year": "2011",
        "color": "#AAAAAA",
        "x": "4",
        "y": "1",
        "percCov": "65.5111917743568"
    },
    "26": {
        "year": "2011",
        "color": "#4daf4a",
        "x": "4",
        "y": "5.5",
        "percCov": "4.22817431573697"
    },
    "27": {
        "year": "2011",
        "color": "#a65628",
        "x": "4",
        "y": "3.7",
        "percCov": "0.492673596062466"
    },
    "28": {
        "year": "2011",
        "color": "#377eb8",
        "x": "4",
        "y": "2.8",
        "percCov": "0.00286122946729027"
    },
    "29": {
        "year": "2012",
        "color": "#ffd300",
        "x": "5",
        "y": "6.4",
        "percCov": "15.6153857042736"
    },
    "30": {
        "year": "2012",
        "color": "#e41a1c",
        "x": "5",
        "y": "1.9",
        "percCov": "0.476861538480073"
    },
    "31": {
        "year": "2012",
        "color": "#f781bf",
        "x": "5",
        "y": "4.6",
        "percCov": "14.3515354712641"
    },
    "32": {
        "year": "2012",
        "color": "#AAAAAA",
        "x": "5",
        "y": "1",
        "percCov": "65.6069676659988"
    },
    "33": {
        "year": "2012",
        "color": "#4daf4a",
        "x": "5",
        "y": "5.5",
        "percCov": "3.64659177875408"
    },
    "34": {
        "year": "2012",
        "color": "#a65628",
        "x": "5",
        "y": "3.7",
        "percCov": "0.302416895590123"
    },
    "35": {
        "year": "2012",
        "color": "#377eb8",
        "x": "5",
        "y": "2.8",
        "percCov": "0.00024094563935076"
    },
    "36": {
        "year": "2013",
        "color": "#ffd300",
        "x": "6",
        "y": "6.4",
        "percCov": "15.9356325771756"
    },
    "37": {
        "year": "2013",
        "color": "#e41a1c",
        "x": "6",
        "y": "1.9",
        "percCov": "0.227181619702848"
    },
    "38": {
        "year": "2013",
        "color": "#f781bf",
        "x": "6",
        "y": "4.6",
        "percCov": "12.1737483099922"
    },
    "39": {
        "year": "2013",
        "color": "#AAAAAA",
        "x": "6",
        "y": "1",
        "percCov": "67.6460002572095"
    },
    "40": {
        "year": "2013",
        "color": "#4daf4a",
        "x": "6",
        "y": "5.5",
        "percCov": "3.79161093543831"
    },
    "41": {
        "year": "2013",
        "color": "#a65628",
        "x": "6",
        "y": "3.7",
        "percCov": "0.223778262547018"
    },
    "42": {
        "year": "2013",
        "color": "#377eb8",
        "x": "6",
        "y": "2.8",
        "percCov": "0.00204803793448146"
    },
    "43": {
        "year": "2014",
        "color": "#ffd300",
        "x": "7",
        "y": "6.4",
        "percCov": "16.0049345666939"
    },
    "44": {
        "year": "2014",
        "color": "#e41a1c",
        "x": "7",
        "y": "1.9",
        "percCov": "0.492221822988684"
    },
    "45": {
        "year": "2014",
        "color": "#f781bf",
        "x": "7",
        "y": "4.6",
        "percCov": "16.5468815460036"
    },
    "46": {
        "year": "2014",
        "color": "#AAAAAA",
        "x": "7",
        "y": "1",
        "percCov": "63.0634551423974"
    },
    "47": {
        "year": "2014",
        "color": "#4daf4a",
        "x": "7",
        "y": "5.5",
        "percCov": "3.75071041315852"
    },
    "48": {
        "year": "2014",
        "color": "#a65628",
        "x": "7",
        "y": "3.7",
        "percCov": "0.137188423405339"
    },
    "49": {
        "year": "2014",
        "color": "#377eb8",
        "x": "7",
        "y": "2.8",
        "percCov": "0.00460808535258328"
    },
    "50": {
        "year": "2015",
        "color": "#ffd300",
        "x": "8",
        "y": "6.4",
        "percCov": "14.3353017588128"
    },
    "51": {
        "year": "2015",
        "color": "#e41a1c",
        "x": "8",
        "y": "1.9",
        "percCov": "1.03639754946237"
    },
    "52": {
        "year": "2015",
        "color": "#f781bf",
        "x": "8",
        "y": "4.6",
        "percCov": "9.72745735186888"
    },
    "53": {
        "year": "2015",
        "color": "#AAAAAA",
        "x": "8",
        "y": "1",
        "percCov": "70.5138858477868"
    },
    "54": {
        "year": "2015",
        "color": "#4daf4a",
        "x": "8",
        "y": "5.5",
        "percCov": "4.0974914245941"
    },
    "55": {
        "year": "2015",
        "color": "#a65628",
        "x": "8",
        "y": "3.7",
        "percCov": "0.288803466966805"
    },
    "56": {
        "year": "2015",
        "color": "#377eb8",
        "x": "8",
        "y": "2.8",
        "percCov": "0.00066260050821459"
    },
    "57": {
        "year": "2016",
        "color": "#ffd300",
        "x": "9",
        "y": "6.4",
        "percCov": "14.7123816843968"
    },
    "58": {
        "year": "2016",
        "color": "#e41a1c",
        "x": "9",
        "y": "1.9",
        "percCov": "0.406565648199488"
    },
    "59": {
        "year": "2016",
        "color": "#f781bf",
        "x": "9",
        "y": "4.6",
        "percCov": "9.68809285803995"
    },
    "60": {
        "year": "2016",
        "color": "#AAAAAA",
        "x": "9",
        "y": "1",
        "percCov": "70.1395165606456"
    },
    "61": {
        "year": "2016",
        "color": "#4daf4a",
        "x": "9",
        "y": "5.5",
        "percCov": "4.8662284869427"
    },
    "62": {
        "year": "2016",
        "color": "#a65628",
        "x": "9",
        "y": "3.7",
        "percCov": "0.185799206144355"
    },
    "63": {
        "year": "2016",
        "color": "#377eb8",
        "x": "9",
        "y": "2.8",
        "percCov": "0.00141555563118571"
    },
    "64": {
        "year": "2017",
        "color": "#ffd300",
        "x": "10",
        "y": "6.4",
        "percCov": "13.9379221631136"
    },
    "65": {
        "year": "2017",
        "color": "#e41a1c",
        "x": "10",
        "y": "1.9",
        "percCov": "0.460597707823896"
    },
    "66": {
        "year": "2017",
        "color": "#f781bf",
        "x": "10",
        "y": "4.6",
        "percCov": "11.182949722777"
    },
    "67": {
        "year": "2017",
        "color": "#AAAAAA",
        "x": "10",
        "y": "1",
        "percCov": "68.1724965973958"
    },
    "68": {
        "year": "2017",
        "color": "#4daf4a",
        "x": "10",
        "y": "5.5",
        "percCov": "6.11110425085332"
    },
    "69": {
        "year": "2017",
        "color": "#a65628",
        "x": "10",
        "y": "3.7",
        "percCov": "0.133634475224915"
    },
    "70": {
        "year": "2017",
        "color": "#377eb8",
        "x": "10",
        "y": "2.8",
        "percCov": "0.00129508281151033"
    },
    "71": {
        "year": "2018",
        "color": "#ffd300",
        "x": "11",
        "y": "6.4",
        "percCov": "13.0477786167371"
    },
    "72": {
        "year": "2018",
        "color": "#e41a1c",
        "x": "11",
        "y": "1.9",
        "percCov": "0.568571472457956"
    },
    "73": {
        "year": "2018",
        "color": "#f781bf",
        "x": "11",
        "y": "4.6",
        "percCov": "11.7820610550226"
    },
    "74": {
        "year": "2018",
        "color": "#AAAAAA",
        "x": "11",
        "y": "1",
        "percCov": "68.113796216009"
    },
    "75": {
        "year": "2018",
        "color": "#4daf4a",
        "x": "11",
        "y": "5.5",
        "percCov": "6.22937844156963"
    },
    "76": {
        "year": "2018",
        "color": "#a65628",
        "x": "11",
        "y": "3.7",
        "percCov": "0.257781715900394"
    },
    "77": {
        "year": "2018",
        "color": "#377eb8",
        "x": "11",
        "y": "2.8",
        "percCov": "0.000632482303295745"
    },
    "78": {
        "year": "2019",
        "color": "#ffd300",
        "x": "12",
        "y": "6.4",
        "percCov": "13.6532448902206"
    },
    "79": {
        "year": "2019",
        "color": "#e41a1c",
        "x": "12",
        "y": "1.9",
        "percCov": "0.54655506466228"
    },
    "80": {
        "year": "2019",
        "color": "#f781bf",
        "x": "12",
        "y": "4.6",
        "percCov": "9.01311376760371"
    },
    "81": {
        "year": "2019",
        "color": "#AAAAAA",
        "x": "12",
        "y": "1",
        "percCov": "71.9304052615299"
    },
    "82": {
        "year": "2019",
        "color": "#4daf4a",
        "x": "12",
        "y": "5.5",
        "percCov": "4.74888796057888"
    },
    "83": {
        "year": "2019",
        "color": "#a65628",
        "x": "12",
        "y": "3.7",
        "percCov": "0.103245206461801"
    },
    "84": {
        "year": "2019",
        "color": "#377eb8",
        "x": "12",
        "y": "2.8",
        "percCov": "0.00454784894274559"
    },
    "85": {
        "year": "2020",
        "color": "#ffd300",
        "x": "13",
        "y": "6.4",
        "percCov": "14.1148364988069"
    },
    "86": {
        "year": "2021",
        "color": "#ffd300",
        "x": "14",
        "y": "6.4",
        "percCov": "14.1966074251615"
    },
    "87": {
        "year": "2021",
        "color": "#e41a1c",
        "x": "14",
        "y": "1.9",
        "percCov": "0.63287383995969"
    },
    "88": {
        "year": "2021",
        "color": "#f781bf",
        "x": "14",
        "y": "4.6",
        "percCov": "7.84401540726891"
    },
    "89": {
        "year": "2021",
        "color": "#AAAAAA",
        "x": "14",
        "y": "1",
        "percCov": "71.4741746934193"
    },
    "90": {
        "year": "2021",
        "color": "#4daf4a",
        "x": "14",
        "y": "5.5",
        "percCov": "5.72827174812989"
    },
    "91": {
        "year": "2021",
        "color": "#a65628",
        "x": "14",
        "y": "3.7",
        "percCov": "0.116738162265443"
    },
    "92": {
        "year": "2021",
        "color": "#377eb8",
        "x": "14",
        "y": "2.8",
        "percCov": "0.00731872379527933"
    },
    "93": {
        "year": "2020",
        "color": "#e41a1c",
        "x": "13",
        "y": "1.9",
        "percCov": "0.873096642392397"
    },
    "94": {
        "year": "2020",
        "color": "#f781bf",
        "x": "13",
        "y": "4.6",
        "percCov": "9.59855143481622"
    },
    "95": {
        "year": "2020",
        "color": "#AAAAAA",
        "x": "13",
        "y": "1",
        "percCov": "70.3053473969287"
    },
    "96": {
        "year": "2020",
        "color": "#4daf4a",
        "x": "13",
        "y": "5.5",
        "percCov": "4.90673747255855"
    },
    "97": {
        "year": "2020",
        "color": "#a65628",
        "x": "13",
        "y": "3.7",
        "percCov": "0.19661164171022"
    },
    "98": {
        "year": "2020",
        "color": "#377eb8",
        "x": "13",
        "y": "2.8",
        "percCov": "0.0048189127870152"
    }
}